<?xml version="1.0" ?>
<stars>
	<default>
		<library path="/root/BASTA/grids/Garstec_AS09_barbieMS.hdf5"/>
		<output path="output/Output/GaiaTheTest/"/>
		<outputfile value="GaiaTheTestResults.ascii"/>
		<solardnu value="135.1"/>
		<solarnumax value="3090.0"/>
		<solarmodel value="True"/>
		<missingval value="-999.999"/>
		<bayesianweights>
			<True/>
		</bayesianweights>
		<fitparams>
			<Teff/>
			<FeH/>
			<logg/>
			<parallax/>
		</fitparams>
		<priors>
			<Teff abstol="300"/>
			<salpeter1955/>
		</priors>
		<distanceInput>
			<filters>
				<G_GAIA/>
			</filters>
			<dustframe value="icrs"/>
		</distanceInput>
		<cornerplots>
			<Teff/>
			<FeH/>
			<radPhot/>
			<massfin/>
			<age/>
			<numax/>
			<dnuscal/>
		</cornerplots>
		<kielplots>
			<True/>
		</kielplots>
		<freqplots>
			<True/>
		</freqplots>
		<outparams>
			<Teff/>
			<FeH/>
			<radPhot/>
			<massfin/>
			<age/>
			<numax/>
			<dnuscal/>
		</outparams>
		<optionaloutputfiles>
			<True/>
		</optionaloutputfiles>
	</default>
	<star starid="1074139748425931008">
		<Teff value="5364.139" error="103.196272"/>
		<FeH value="0.3159" error="0.130806154"/>
		<logg value="4.4623" error="0.160094503"/>
		<parallax value="6.7328124693775075" error="0.012559627"/>
		<G_GAIA value="10.989216" error="0.5"/>
		<RA value="167.8215134310371"/>
		<DEC value="69.96477708833692"/>
	</star>
	<star starid="1076970406751899008">
		<Teff value="6437.147" error="102.0064646"/>
		<FeH value="-0.0366" error="0.130216166"/>
		<logg value="4.1884" error="0.160010695"/>
		<parallax value="10.343980152928568" error="0.018026635"/>
		<G_GAIA value="8.24857" error="0.5"/>
		<RA value="161.90900262984917"/>
		<DEC value="71.65572225"/>
	</star>
	<star starid="1111639314047794944">
		<Teff value="6056.1055" error="102.0273909"/>
		<FeH value="-0.0286" error="0.130063071"/>
		<logg value="4.2878" error="0.160261419"/>
		<parallax value="3.1211708877055027" error="0.020112157"/>
		<G_GAIA value="11.409017" error="0.5"/>
		<RA value="105.4045529987421"/>
		<DEC value="72.41492935805954"/>
	</star>
	<star starid="111322601672419712">
		<Teff value="5040.7104" error="124.1327797"/>
		<FeH value="-0.2544" error="0.152225622"/>
		<logg value="4.3441" error="0.161956815"/>
		<parallax value="3.336455878156213" error="0.017776499"/>
		<G_GAIA value="12.832714" error="0.5"/>
		<RA value="48.43547511190464"/>
		<DEC value="25.19735288979064"/>
	</star>
	<star starid="1117620107545810944">
		<Teff value="5885.8667" error="102.0416403"/>
		<FeH value="0.3149" error="0.13001696"/>
		<logg value="4.2059" error="0.160056435"/>
		<parallax value="2.386256501056703" error="0.010788254"/>
		<G_GAIA value="12.024529" error="0.5"/>
		<RA value="139.1125645868252"/>
		<DEC value="69.07412832389238"/>
	</star>
	<star starid="1255520718461480960">
		<Teff value="5694.083" error="102.0231047"/>
		<FeH value="-0.0327" error="0.130096118"/>
		<logg value="4.2388" error="0.16004875"/>
		<parallax value="2.169656920316102" error="0.012602167"/>
		<G_GAIA value="12.297648" error="0.5"/>
		<RA value="215.8014968021862"/>
		<DEC value="24.076563805074205"/>
	</star>
	<star starid="1316708918505350528">
		<Teff value="5848.95" error="102.2890663"/>
		<FeH value="-0.021" error="0.130216166"/>
		<logg value="4.5317" error="0.160039378"/>
		<parallax value="6.1806301217187425" error="0.013609672"/>
		<G_GAIA value="11.003223" error="0.5"/>
		<RA value="240.54927183235347"/>
		<DEC value="28.169626854398295"/>
	</star>
	<star starid="1331356474971716992">
		<Teff value="5974.0513" error="102.0124504"/>
		<FeH value="0.0281" error="0.130105966"/>
		<logg value="4.118" error="0.16000957"/>
		<parallax value="13.14239297582366" error="0.016170053"/>
		<G_GAIA value="8.026566" error="0.5"/>
		<RA value="247.6229689231794"/>
		<DEC value="38.34754219061385"/>
	</star>
	<star starid="1344163891352965632">
		<Teff value="5992.018" error="102.1657183"/>
		<FeH value="-0.2277" error="0.130031237"/>
		<logg value="3.6662" error="0.160067556"/>
		<parallax value="4.438533900254725" error="0.012652458"/>
		<G_GAIA value="8.94528" error="0.5"/>
		<RA value="263.7580742016062"/>
		<DEC value="40.69504234663025"/>
	</star>
	<star starid="1416731285125373184">
		<Teff value="6151.7153" error="103.8530691"/>
		<FeH value="0.0051" error="0.131074645"/>
		<logg value="4.112" error="0.160053811"/>
		<parallax value="1.8688549534871162" error="0.011940389"/>
		<G_GAIA value="11.909978" error="0.5"/>
		<RA value="264.26301875574205"/>
		<DEC value="53.02127600650236"/>
	</star>
	<star starid="1424011082893734272">
		<Teff value="5903.319" error="102.0377643"/>
		<FeH value="-0.1756" error="0.130140703"/>
		<logg value="4.1877" error="0.160082861"/>
		<parallax value="1.7206405270914615" error="0.010691544"/>
		<G_GAIA value="12.810718" error="0.5"/>
		<RA value="246.6920383450211"/>
		<DEC value="51.04113442310046"/>
	</star>
	<star starid="1464700950221781504">
		<Teff value="6204.659" error="104.6547348"/>
		<FeH value="-0.4268" error="0.132663493"/>
		<logg value="4.0163" error="0.160813005"/>
		<parallax value="4.131811806491365" error="0.017634887"/>
		<G_GAIA value="10.197724" error="0.5"/>
		<RA value="195.98183545376395"/>
		<DEC value="30.640147243322442"/>
	</star>
	<star starid="1587399232335653760">
		<Teff value="5840.252" error="102.8701506"/>
		<FeH value="0.1282" error="0.130498889"/>
		<logg value="4.036" error="0.160515178"/>
		<parallax value="2.320259904580209" error="0.010866479"/>
		<G_GAIA value="11.599696" error="0.5"/>
		<RA value="224.8728600560122"/>
		<DEC value="46.960098488386336"/>
	</star>
	<star starid="1675923009431370880">
		<Teff value="5188.1562" error="102.6942968"/>
		<FeH value="0.2027" error="0.130419333"/>
		<logg value="4.4934" error="0.160017999"/>
		<parallax value="9.107038344521502" error="0.010974641"/>
		<G_GAIA value="10.689707" error="0.5"/>
		<RA value="198.38856310063383"/>
		<DEC value="62.30537777748986"/>
	</star>
	<star starid="1725490333641502976">
		<Teff value="5848.7705" error="102.0501367"/>
		<FeH value="0.1182" error="0.130120559"/>
		<logg value="4.3597" error="0.160061871"/>
		<parallax value="3.3098700303284447" error="0.01116791"/>
		<G_GAIA value="11.700803" error="0.5"/>
		<RA value="217.9257592"/>
		<DEC value="83.37270756863437"/>
	</star>
	<star starid="1737061349198867456">
		<Teff value="5997.613" error="102.9522941"/>
		<FeH value="-0.202" error="0.130552671"/>
		<logg value="4.0346" error="0.160241817"/>
		<parallax value="2.134653769458227" error="0.033424024"/>
		<G_GAIA value="11.453518" error="0.5"/>
		<RA value="315.53194768088133"/>
		<DEC value="7.056279987"/>
	</star>
	<star starid="1750321012752775040">
		<Teff value="6138.781" error="102.0647965"/>
		<FeH value="-0.1752" error="0.130040619"/>
		<logg value="4.027" error="0.16008942"/>
		<parallax value="1.7081089291347222" error="0.015179253"/>
		<G_GAIA value="11.931145" error="0.5"/>
		<RA value="313.6872919470238"/>
		<DEC value="9.179068007"/>
	</star>
	<star starid="1779546757669063552">
		<Teff value="5996.3154" error="102.0120614"/>
		<FeH value="-0.3061" error="0.130548085"/>
		<logg value="4.237" error="0.160027193"/>
		<parallax value="20.80311089" error="0.02657181"/>
		<G_GAIA value="7.5212455" error="0.5"/>
		<RA value="330.79502626424147"/>
		<DEC value="18.88423938290383"/>
	</star>
	<star starid="179498266829041664">
		<Teff value="5372.22" error="106.9155578"/>
		<FeH value="-0.0133" error="0.134746809"/>
		<logg value="4.3559" error="0.160061871"/>
		<parallax value="5.223475406073244" error="0.01663114"/>
		<G_GAIA value="11.716202" error="0.5"/>
		<RA value="66.24814452059672"/>
		<DEC value="39.460600684443286"/>
	</star>
	<star starid="1808938730710633984">
		<Teff value="5774.3516" error="102.2165146"/>
		<FeH value="-0.1446" error="0.130202007"/>
		<logg value="4.2393" error="0.160069016"/>
		<parallax value="2.7586656044941975" error="0.010759043"/>
		<G_GAIA value="12.162349" error="0.5"/>
		<RA value="306.1239095151492"/>
		<DEC value="16.762145396892375"/>
	</star>
</stars>

